LICENSE
MANIFEST.in
README.md
setup.py
aitextgen/TokenDataset.py
aitextgen/__init__.py
aitextgen/aitextgen.py
aitextgen/cli.py
aitextgen/colab.py
aitextgen/tokenizers.py
aitextgen/train.py
aitextgen/utils.py
aitextgen.egg-info/PKG-INFO
aitextgen.egg-info/SOURCES.txt
aitextgen.egg-info/dependency_links.txt
aitextgen.egg-info/entry_points.txt
aitextgen.egg-info/requires.txt
aitextgen.egg-info/top_level.txt
aitextgen/static/gpt2_merges.txt
aitextgen/static/gpt2_vocab.json